LICENSE
MANIFEST.in
README.md
setup.py
apush/__init__.py
apush/notification.py
apush/service.py
apush.egg-info/PKG-INFO
apush.egg-info/SOURCES.txt
apush.egg-info/dependency_links.txt
apush.egg-info/top_level.txt