Metadata-Version: 1.0
Name: apush
Version: 0.2.0
Summary: A simple Apple push notification service provider
Home-page: https://github.com/barumrho/apush
Author: Barum Rho
Author-email: barum@barumrho.com
License: (The MIT License)
